lorax/__init__.py
lorax/client.py
lorax/errors.py
lorax/types.py
lorax_client-0.6.3.dist-info/METADATA
lorax_client-0.6.3.dist-info/WHEEL
lorax_client-0.6.3.dist-info/RECORD
