Metadata-Version: 2.1
Name: lorax-client
Version: 0.6.3
Summary: LoRAX Python Client
Home-page: https://github.com/predibase/lorax
License: Apache-2.0
Author: Travis Addair
Author-email: travis@predibase.com
Maintainer: Travis Addair
Maintainer-email: travis@predibase.com
Requires-Python: >=3.8,<4.0
Classifier: License :: OSI Approved :: Apache Software License
Classifier: Programming Language :: Python :: 3
Classifier: Programming Language :: Python :: 3.8
Classifier: Programming Language :: Python :: 3.9
Classifier: Programming Language :: Python :: 3.10
Classifier: Programming Language :: Python :: 3.11
Classifier: Programming Language :: Python :: 3.12
Requires-Dist: aiohttp (>=3.9,<4.0)
Requires-Dist: certifi (==2024.7.4)
Requires-Dist: huggingface-hub (>=0.12,<1.0)
Requires-Dist: pydantic (>2,<3)
Project-URL: Repository, https://github.com/predibase/lorax
